rich_life/__init__.py
rich_life/__main__.py
rich_life/py.typed
rich_life-0.3.1.dist-info/METADATA
rich_life-0.3.1.dist-info/WHEEL
rich_life-0.3.1.dist-info/entry_points.txt
rich_life-0.3.1.dist-info/licenses/LICENSE
rich_life-0.3.1.dist-info/RECORD
