Metadata-Version: 2.4
Name: rich_life
Version: 0.3.1
Summary: Terminal-based life and ant simulation.
Project-URL: Homepage, https://github.com/paulrobello/rich_life
Project-URL: Documentation, https://github.com/paulrobello/rich_life/blob/main/README.md
Project-URL: Repository, https://github.com/paulrobello/rich_life
Project-URL: Issues, https://github.com/paulrobello/rich_life/issues
Project-URL: Discussions, https://github.com/paulrobello/rich_life/discussions
Project-URL: Wiki, https://github.com/paulrobello/rich_life/wiki
Author-email: Paul Robello <probello@gmail.com>
Maintainer-email: Paul Robello <probello@gmail.com>
License: MIT License
License-File: LICENSE
Keywords: simulation,terminal
Classifier: Development Status :: 4 - Beta
Classifier: Environment :: Console
Classifier: Intended Audience :: Developers
Classifier: License :: OSI Approved :: MIT License
Classifier: Programming Language :: Python :: 3
Classifier: Programming Language :: Python :: 3.11
Classifier: Programming Language :: Python :: 3.12
Classifier: Programming Language :: Python :: 3.13
Classifier: Topic :: Games/Entertainment :: Simulation
Classifier: Typing :: Typed
Requires-Python: >=3.11
Requires-Dist: rich>=14.2.0
Requires-Dist: typer>=0.20.0
Provides-Extra: dev
Requires-Dist: pytest>=7.4.0; extra == 'dev'
